redgettext.py
redgettext-3.4.2.dist-info/LICENSE
redgettext-3.4.2.dist-info/METADATA
redgettext-3.4.2.dist-info/WHEEL
redgettext-3.4.2.dist-info/entry_points.txt
redgettext-3.4.2.dist-info/top_level.txt
redgettext-3.4.2.dist-info/RECORD
