Metadata-Version: 2.1
Name: redgettext
Version: 3.4.2
Summary: "A slightly modified pygettext for Red-DiscordBot"
Home-page: https://github.com/Tobotimus/redgettext
Author: Toby Harradine
Author-email: me@tobyharradine.id.au
License: GPL-3.0
Keywords: gettext,redbot,red-discordbot
Platform: UNKNOWN
Classifier: Programming Language :: Python :: 3
Classifier: Programming Language :: Python :: 3.6
Classifier: Programming Language :: Python :: 3.7
Classifier: Programming Language :: Python :: 3.8
Requires-Python: >=3.6
License-File: LICENSE
Requires-Dist: polib
